{
    "Title": "Deutschland",
    "Submaps": [
        {"Name": "BB"},
        {"Name": "BE"},
        {"Name": "BW"},
        {"Name": "BY"},
        {"Name": "HB"},
        {"Name": "HE"},
        {"Name": "HH"},
        {"Name": "MV"},
        {"Name": "NI"},
        {"Name": "NW"},
        {"Name": "RP"},
        {"Name": "SH"},
        {"Name": "SL"},
        {"Name": "SN"},
        {"Name": "ST"},
        {"Name": "TH"}
    ],
    "Figure Size": [12, 18],
    "Cropping": {
        "small": [0.000, 0.150, 0.890, 0.850],
        "large": [0.000, 0.150, 1.000, 0.850]
    },
    "Plotting Area": {
        "xlims": [5.7, 15.3],
        "ylims": [47.1, 55.2]
    },
    "Colors": {
        "map_dark": "#843c39",
        "map_light": "#bd9e39",
        "unvisited": "#e7ba52",
        "active": "#EAEAEA",
        "visited": "#b5524e"
    },
    "Marker Size": 75,
    "Labels": {
        "Start Longitude": 4.7, 
        "Start Latitude": 47.2,
        "Vertical Spacing": 0.069,
        "Horizontal Spacing": 1.45,
        "Font": 5.5,
        "Splits": 27,
        "Longitude Threshold": 1.0,
        "Latitude THreshold": 0.08,
        "Shift Step": 0.06
    },
    "Flags": {
        "Scale": {
            "small": 0.20,
            "large": 0.75
        },
        "Radius": {
            "small": 0.85,
            "large": 2.75
        },
        "Linewidth": {
            "small": 1,
            "large": 10,
            "color": "#e7ba52"
        },
        "Position": {
            "x_start": -0.075,
            "y_start": 0.94,
            "x_spacing": 0.0825,
            "y_spacing": 0.057,
            "num_in_row": 1
        }
    }
}